bridgepoint/__init__.py
bridgepoint/__oal_lextab.py
bridgepoint/__oal_parsetab.py
bridgepoint/consistency_check.py
bridgepoint/external_entities.py
bridgepoint/gen_pyxtuml_schema.py
bridgepoint/gen_sql_schema.py
bridgepoint/gen_xsd_schema.py
bridgepoint/imp.py
bridgepoint/interpret.py
bridgepoint/oal.py
bridgepoint/ooaofooa.py
bridgepoint/prebuild.py
bridgepoint/schema.py
bridgepoint/sourcegen.py
xtuml/__init__.py
xtuml/__xtuml_lextab.py
xtuml/__xtuml_parsetab.py
xtuml/consistency_check.py
xtuml/load.py
xtuml/meta.py
xtuml/persist.py
xtuml/tools.py
xtuml/version.py
pyxtuml-3.0.0.dist-info/AUTHORS
pyxtuml-3.0.0.dist-info/COPYING
pyxtuml-3.0.0.dist-info/COPYING.LESSER
pyxtuml-3.0.0.dist-info/METADATA
pyxtuml-3.0.0.dist-info/WHEEL
pyxtuml-3.0.0.dist-info/top_level.txt
pyxtuml-3.0.0.dist-info/RECORD
