Metadata-Version: 2.1
Name: pyxtuml
Version: 3.0.0
Summary: Library for parsing, manipulating, and generating BridgePoint xtUML models
Home-page: https://github.com/xtuml/pyxtuml
Author: John Törnblom
Author-email: john.tornblom@gmail.com
License: LGPLv3+
Keywords: xtuml bridgepoint
Classifier: Development Status :: 4 - Beta
Classifier: Intended Audience :: Developers
Classifier: Topic :: Software Development :: Code Generators
Classifier: Topic :: Software Development :: Compilers
Classifier: License :: OSI Approved :: GNU Lesser General Public License v3 or later (LGPLv3+)
Classifier: Programming Language :: Python :: 3 :: Only
Requires: ply
License-File: COPYING
License-File: COPYING.LESSER
License-File: AUTHORS
Requires-Dist: ply
